keychecker/__init__.py
keychecker/__main__.py
keychecker/cli.py
keychecker/core/__init__.py
keychecker/core/key_analyzer.py
keychecker/core/server_validator.py
keychecker/plugins/__init__.py
keychecker/plugins/base.py
keychecker/plugins/bitbucket.py
keychecker/plugins/codeberg.py
keychecker/plugins/gitea.py
keychecker/plugins/github.py
keychecker/plugins/gitlab.py
keychecker/plugins/huggingface.py
keychecker/utils/__init__.py
keychecker/utils/output.py
keychecker-1.1.0.dist-info/licenses/LICENSE
keychecker-1.1.0.dist-info/METADATA
keychecker-1.1.0.dist-info/WHEEL
keychecker-1.1.0.dist-info/entry_points.txt
keychecker-1.1.0.dist-info/top_level.txt
keychecker-1.1.0.dist-info/RECORD
