Metadata-Version: 2.4
Name: keychecker
Version: 1.1.0
Summary: A fast CLI to fingerprint SSH private keys and identify which Git hosting accounts they unlock
Author-email: Cyfinoid Research <keychecker@cyfinoid.com>
Project-URL: Homepage, https://github.com/cyfinoid/keychecker
Project-URL: Bug Reports, https://github.com/cyfinoid/keychecker/issues
Project-URL: Source, https://github.com/cyfinoid/keychecker
Project-URL: Documentation, https://github.com/cyfinoid/keychecker#readme
Keywords: ssh,key,fingerprint,git,github,gitlab,bitbucket,security,audit
Classifier: Development Status :: 4 - Beta
Classifier: Intended Audience :: Developers
Classifier: Intended Audience :: System Administrators
Classifier: Operating System :: OS Independent
Classifier: Programming Language :: Python :: 3
Classifier: Programming Language :: Python :: 3.9
Classifier: Programming Language :: Python :: 3.10
Classifier: Programming Language :: Python :: 3.11
Classifier: Programming Language :: Python :: 3.12
Classifier: Programming Language :: Python :: 3.13
Classifier: Topic :: Security
Classifier: Topic :: Software Development :: Version Control :: Git
Classifier: Topic :: System :: Systems Administration
Classifier: Topic :: Utilities
Requires-Python: >=3.9
License-File: LICENSE
Requires-Dist: cryptography>=45.0.6
Requires-Dist: asyncssh>=2.21.0
Requires-Dist: aiohttp>=3.12.15
Requires-Dist: tqdm>=4.67.1
Provides-Extra: dev
Requires-Dist: pytest>=8.4.1; extra == "dev"
Requires-Dist: pytest-asyncio>=1.1.0; extra == "dev"
Requires-Dist: black>=25.1.0; extra == "dev"
Requires-Dist: flake8>=7.3.0; extra == "dev"
Requires-Dist: mypy>=1.17.1; extra == "dev"
Requires-Dist: types-tqdm>=4.0.0; extra == "dev"
Requires-Dist: bandit>=1.7.0; extra == "dev"
Requires-Dist: pip-audit>=2.6.0; extra == "dev"
Dynamic: license-file
